{
  "build": {
    "dockerfile": "Dockerfile",
    "context": "../.."
  },
  "privileged": true,
  "remoteEnv": {
    "CONTAINER_FLAVOR": "rust"
  },
  "mounts": [
    "source=/var/run/docker.sock,target=/var/run/docker.sock,type=bind"
  ],
  "customizations": {
    "vscode": {
      "settings": {
        "files.insertFinalNewline": true,
        "files.trimTrailingWhitespace": true,
        "git.alwaysSignOff": true
      },
      "extensions": [
        "github.copilot@1.208.0",
        "github.vscode-github-actions@0.26.3",
        "github.vscode-pull-request-github@0.90.0",
        "jetmartin.bats@0.1.10",
        "mhutchie.git-graph@1.30.0",
        "ms-azuretools.vscode-docker@1.29.1",
        "rust-lang.rust-analyzer@0.3.2020",
        "sonarsource.sonarlint-vscode@4.7.0",
        "tamasfe.even-better-toml@0.19.2",
        "usernamehw.errorlens@3.20.0"
      ]
    }
  }
}
